LightBerries/LightBerryExceptions.py
LightBerries/LightControls.py
LightBerries/LightFunctions.py
LightBerries/LightPatterns.py
LightBerries/LightPixels.py
LightBerries/LightStrings.py
LightBerries/RpiWS281xPatch.py
LightBerries/__init__.py
LightBerries/__main__.py
LightBerries-1.0.1.dist-info/LICENSE
LightBerries-1.0.1.dist-info/METADATA
LightBerries-1.0.1.dist-info/WHEEL
LightBerries-1.0.1.dist-info/top_level.txt
LightBerries-1.0.1.dist-info/RECORD
