Metadata-Version: 2.1
Name: LightBerries
Version: 1.0.1
Summary: A wrapper for rpi_ws281x that does all the heavy lifting for you.
Home-page: https://github.com/joeferg425/ws281x_lightberries
Author: JoeFerg425
License: MIT
Keywords: raspberry pi rpi rpi_ws281x adafruit neopixel
Platform: UNKNOWN
Classifier: Programming Language :: Python :: 3
Classifier: Programming Language :: Python :: 3
Requires-Python: >=3.7
License-File: LICENSE
Requires-Dist: Adafruit-Blinka (>=3.0.0)
Requires-Dist: adafruit-circuitpython-neopixel (==3.4.0)
Requires-Dist: numpy (>=1.15.1)
Requires-Dist: rpi-ws281x (==4.2.2)
Requires-Dist: RPi.GPIO (>=0.7.0)
Requires-Dist: nptyping (>=1.4.4)
